SentencePolarity
