Metadata-Version: 1.0
Name: SentencePolarity
Version: 1.0
Summary: SentencePolarity python 3 claire
Home-page: UNKNOWN
Author: UNKNOWN
Author-email: UNKNOWN
License: UNKNOWN
Platform: UNKNOWN
